[
  {
    "id": "0212a03e-3290-4c8d-a384-3b3c94ce4159",
    "name": "Test Product",
    "image": "/products/0212a03e-3290-4c8d-a384-3b3c94ce4159.jpg",
    "price": 100,
    "variants": [
      {
        "id": 1,
        "name": "Black"
      },
      {
        "id": 2,
        "name": "White"
      }
    ]
  },
  {
    "id": "c0026cac-c4fe-49b1-b826-fb1bbe0ca860",
    "name": "Test Product 2",
    "image": "/products/c0026cac-c4fe-49b1-b826-fb1bbe0ca860.jpg",
    "price": 200,
    "variants": [
      {
        "id": 1,
        "name": "Black"
      },
      {
        "id": 2,
        "name": "White"
      }
    ]
  }
]